Metadata-Version: 2.1
Name: pedl
Version: 1.0.2
Summary: Search the biomedical literature for protein interactions andprotein associations.
Home-page: https://github.com/leonweber/pedl
Author: Leon Weber
Author-email: leonweber@posteo.de
License: MIT
Requires-Dist: requests
Requires-Dist: numpy
Requires-Dist: tqdm
Requires-Dist: torch (>=1.8)
Requires-Dist: transformers (>=4.6)
Requires-Dist: lxml (>=4.4.1)
Requires-Dist: bioc
Requires-Dist: segtok
Requires-Dist: diskcache
Requires-Dist: openpyxl
Requires-Dist: pandas
Requires-Dist: entrezpy
Requires-Dist: hydra-core
Requires-Dist: elasticsearch
Requires-Dist: pytorch-lightning
Requires-Dist: biopython
